Metadata-Version: 1.1
Name: pyeddl
Version: 1.3.1
Summary: Python wrapper for EDDL
Home-page: https://github.com/deephealthproject/pyeddl
Author: Simone Leo
Author-email: <simone.leo@crs4.it>
License: BSD
Platform: Linux
Classifier: Programming Language :: Python :: 3.6
Classifier: License :: OSI Approved :: BSD License
Classifier: Operating System :: POSIX :: Linux
Classifier: Topic :: Scientific/Engineering
Classifier: Intended Audience :: Science/Research
